{
  "parent": "foodexpansion:recipes/root",
  "rewards": {
    "recipes": [
      "foodexpansion:bucket_caramel_custard"
    ]
  },
  "criteria": {
    "has_ingredients": {
      "trigger": "minecraft:inventory_changed",
      "conditions": {
        "items": [
          {
            "items": [
              "minecraft:milk_bucket"
            ]
          }
        ]
      }
    },
    "has_the_recipe": {
      "trigger": "minecraft:recipe_unlocked",
      "conditions": {
        "recipe": "foodexpansion:bucket_caramel_custard"
      }
    }
  },
  "requirements": [
    [
      "has_ingredients",
      "has_the_recipe"
    ]
  ]
}
